{"0":{"gene":"UBC","risk":0.0049063774},"1":{"gene":"NDUFA8","risk":0.0043494621},"2":{"gene":"NDUFS4","risk":0.0043486485},"3":{"gene":"NDUFS8","risk":0.0043440799},"4":{"gene":"NDUFS3","risk":0.004336659},"5":{"gene":"NDUFS2","risk":0.0043363456},"6":{"gene":"MT-ND2","risk":0.00433626},"7":{"gene":"MT-ND5","risk":0.0043286954},"8":{"gene":"MT-ND3","risk":0.004328687},"9":{"gene":"COXFA4","risk":0.0042926843},"10":{"gene":"NDUFV2","risk":0.0042831598},"11":{"gene":"NDUFA9","risk":0.0042757025},"12":{"gene":"NDUFB6","risk":0.0042717268},"13":{"gene":"NDUFB8","risk":0.0042679714},"14":{"gene":"NDUFV1","risk":0.0042674958},"15":{"gene":"NDUFA11","risk":0.0042624216},"16":{"gene":"NDUFS7","risk":0.0042622908},"17":{"gene":"NDUFB4","risk":0.0042621724},"18":{"gene":"NDUFS5","risk":0.0042610861},"19":{"gene":"NDUFC2","risk":0.0042605355},"20":{"gene":"NDUFB11","risk":0.0042600203},"21":{"gene":"NDUFS6","risk":0.0042593077},"22":{"gene":"NDUFA10","risk":0.0042569791},"23":{"gene":"NDUFA12","risk":0.0042567933},"24":{"gene":"MT-ND1","risk":0.0042492167},"26":{"gene":"NDUFB10","risk":0.0042443664},"27":{"gene":"NDUFB1","risk":0.004239198},"28":{"gene":"MT-ND4","risk":0.0042385439},"29":{"gene":"MT-ND4L","risk":0.0042384271},"31":{"gene":"NDUFB2","risk":0.0042381444},"32":{"gene":"NDUFAB1","risk":0.0042380657},"33":{"gene":"NDUFB3","risk":0.0042379464},"34":{"gene":"NDUFA5","risk":0.0042376231},"35":{"gene":"NDUFA13","risk":0.0042376183},"36":{"gene":"NDUFA2","risk":0.0042310895},"37":{"gene":"NDUFA1","risk":0.0042297873},"38":{"gene":"NDUFB7","risk":0.0042295993},"39":{"gene":"NDUFB5","risk":0.0042295069},"40":{"gene":"NDUFV3","risk":0.0042266807},"41":{"gene":"NDUFB9","risk":0.0042096314},"42":{"gene":"GABRA1","risk":0.0041301757},"43":{"gene":"GABRG2","risk":0.0040747304},"44":{"gene":"GABRB3","risk":0.0040676641},"45":{"gene":"GABRA2","risk":0.0039927087},"46":{"gene":"MT-ND6","risk":0.0039524067},"47":{"gene":"GABRA5","risk":0.0039424608},"49":{"gene":"GABRA6","risk":0.0039398527},"50":{"gene":"GABRA4","risk":0.0039364108},"51":{"gene":"GABRB2","risk":0.0038828032},"52":{"gene":"GABRB1","risk":0.0038822432},"53":{"gene":"NDUFA7","risk":0.0036131384},"54":{"gene":"NDUFA6","risk":0.0035992461},"55":{"gene":"NDUFAF1","risk":0.0035930343},"56":{"gene":"GABRD","risk":0.0035414828},"57":{"gene":"GABRG1","risk":0.0034583541},"58":{"gene":"GABRE","risk":0.0034272564},"59":{"gene":"GABRP","risk":0.003414947},"60":{"gene":"CYC1","risk":0.003152079},"61":{"gene":"MT-CYB","risk":0.0031354995},"62":{"gene":"UQCRH","risk":0.0031180951},"63":{"gene":"UQCR10","risk":0.0031124706},"64":{"gene":"UQCRB","risk":0.0031120279},"65":{"gene":"UQCRFS1","risk":0.0030896785},"66":{"gene":"UQCRQ","risk":0.0030828763},"67":{"gene":"UQCRC2","risk":0.0030781188},"68":{"gene":"UQCRC1","risk":0.0030594181},"71":{"gene":"CYCS","risk":0.0024151462},"72":{"gene":"GABRG3","risk":0.00241293},"73":{"gene":"GLRB","risk":0.0022531049},"74":{"gene":"PDE3A","risk":0.0020687101},"75":{"gene":"PDE10A","risk":0.0020547713},"76":{"gene":"PDE2A","risk":0.0020507102},"77":{"gene":"PDE1B","risk":0.0020480985},"79":{"gene":"SLC29A1","risk":0.0019843678},"80":{"gene":"PDE1C","risk":0.0018904106},"81":{"gene":"GLRA1","risk":0.0018090133},"82":{"gene":"GPHN","risk":0.001773358},"83":{"gene":"PDE6G","risk":0.0016998563},"84":{"gene":"GABARAP","risk":0.0016890734},"85":{"gene":"PDE6H","risk":0.001682836},"86":{"gene":"PDE6B","risk":0.0016762046},"87":{"gene":"PDE6A","risk":0.0016760585},"88":{"gene":"PDE7B","risk":0.0016534157},"89":{"gene":"PDE5A","risk":0.001640046},"90":{"gene":"PDE9A","risk":0.001634967},"91":{"gene":"TUBA4A","risk":0.0016317877},"92":{"gene":"PDE6C","risk":0.0016238561},"93":{"gene":"TUBA1A","risk":0.0016225553},"94":{"gene":"TUBB4B","risk":0.0016210573},"95":{"gene":"PDE4B","risk":0.0016210568},"96":{"gene":"TUBB4A","risk":0.0016184164},"97":{"gene":"PDE6D","risk":0.0016160063},"98":{"gene":"PDE8A","risk":0.0016138882},"99":{"gene":"PDE7A","risk":0.0016050498},"100":{"gene":"NDUFAF4","risk":0.0016019361},"101":{"gene":"PDE4D","risk":0.0016001981},"102":{"gene":"PLCL1","risk":0.0015891143},"103":{"gene":"PDE4C","risk":0.0015853823},"105":{"gene":"TRAK2","risk":0.0015682498},"106":{"gene":"TUBB1","risk":0.0015547166},"107":{"gene":"TUBB2A","risk":0.0015542103},"108":{"gene":"TUBB6","risk":0.001550165},"109":{"gene":"TUBB2B","risk":0.0015496542},"110":{"gene":"TUBA1C","risk":0.001535003},"111":{"gene":"GABARAPL2","risk":0.0015260322},"112":{"gene":"NSF","risk":0.0015032394},"113":{"gene":"TUBA1B","risk":0.0015007892},"114":{"gene":"CHRNA4","risk":0.0014665762},"115":{"gene":"CHRNB2","risk":0.0014549474},"116":{"gene":"REN","risk":0.001428662},"117":{"gene":"KCNK9","risk":0.0014042532},"118":{"gene":"GUCY1A2","risk":0.0013831374},"119":{"gene":"GUCY1B1","risk":0.0013825531},"120":{"gene":"GUCY1A1","risk":0.0013818671},"121":{"gene":"GABARAPL1","risk":0.0013796468},"122":{"gene":"RXFP1","risk":0.0013775361},"123":{"gene":"ADRB2","risk":0.0013706395},"124":{"gene":"SCNN1A","risk":0.0013703257},"125":{"gene":"SCNN1G","risk":0.0013702678},"127":{"gene":"GRIN1","risk":0.0013675208},"128":{"gene":"SCNN1B","risk":0.0013671651},"129":{"gene":"RXFP2","risk":0.0013661257},"130":{"gene":"CACNA1D","risk":0.0013626714},"131":{"gene":"GRIN2A","risk":0.001360376},"132":{"gene":"ADORA2A","risk":0.0013594347},"133":{"gene":"ADORA2B","risk":0.0013593957},"134":{"gene":"ADRB1","risk":0.0013549791},"135":{"gene":"ETFDH","risk":0.0013514304},"136":{"gene":"CACNA1C","risk":0.0013510015},"137":{"gene":"ENTPD3","risk":0.0013467411},"138":{"gene":"ENTPD8","risk":0.0013466691},"139":{"gene":"ENTPD1","risk":0.001345084},"140":{"gene":"NR3C2","risk":0.0013344183},"141":{"gene":"KCNK3","risk":0.0013224196},"142":{"gene":"GLP1R","risk":0.0013183143},"143":{"gene":"PTGER2","risk":0.0013181527},"144":{"gene":"SCN5A","risk":0.0013088969},"145":{"gene":"ACE","risk":0.0013053281},"146":{"gene":"TUBA3E","risk":0.0012878806},"147":{"gene":"CACNA1S","risk":0.0012868598},"148":{"gene":"GRIN2D","risk":0.0012504755},"149":{"gene":"TUBA3C","risk":0.0012424052},"150":{"gene":"GRIN2C","risk":0.0012398968},"151":{"gene":"TLR7","risk":0.0012275319},"152":{"gene":"GRIN3A","risk":0.0012273226},"153":{"gene":"GRIN3B","risk":0.0012271303},"154":{"gene":"NDUFAF3","risk":0.0012239898},"155":{"gene":"TLR9","risk":0.0012201822},"156":{"gene":"PDE3B","risk":0.001217349},"157":{"gene":"F2","risk":0.0012169842},"158":{"gene":"OPRM1","risk":0.0012039542},"159":{"gene":"PDE11A","risk":0.0011941286},"160":{"gene":"SLC6A4","risk":0.001191216},"161":{"gene":"ADRA2A","risk":0.0011737078},"163":{"gene":"ADRA2C","risk":0.0011730784},"164":{"gene":"ADORA1","risk":0.0011690279},"165":{"gene":"P2RY12","risk":0.0011665967},"166":{"gene":"AR","risk":0.0011478978},"167":{"gene":"CETP","risk":0.0011460551},"168":{"gene":"F2R","risk":0.001141234},"169":{"gene":"F9","risk":0.0011394335},"170":{"gene":"PLG","risk":0.0011270026},"171":{"gene":"PLA2G2A","risk":0.0011202031},"172":{"gene":"PTGS2","risk":0.0011173972},"173":{"gene":"ITGAV","risk":0.0011169023},"174":{"gene":"FDPS","risk":0.0011136374},"175":{"gene":"SERPINC1","risk":0.0011083178},"176":{"gene":"PPARG","risk":0.001102429},"177":{"gene":"ATP4A","risk":0.0010979943},"178":{"gene":"PTGS1","risk":0.001097205},"179":{"gene":"PTGER1","risk":0.0010969417},"180":{"gene":"XDH","risk":0.0010811631},"181":{"gene":"CACNA1F","risk":0.0010811039},"182":{"gene":"AGTR1","risk":0.0010753565},"183":{"gene":"APRT","risk":0.0010737161},"185":{"gene":"ITGA2B","risk":0.001061545},"186":{"gene":"GPD2","risk":0.0010475793},"187":{"gene":"ATP4B","risk":0.0010448067},"188":{"gene":"ITPA","risk":0.0010376831},"189":{"gene":"PCSK9","risk":0.0010205904},"190":{"gene":"NR3C1","risk":0.0010098171},"191":{"gene":"PAH","risk":0.0010098069},"192":{"gene":"ADCY3","risk":0.0010070488},"193":{"gene":"HMGCR","risk":0.0010045595},"194":{"gene":"DHFR","risk":0.0009984911},"195":{"gene":"ADCY9","risk":0.0009950454},"196":{"gene":"ADCY7","risk":0.0009939327},"197":{"gene":"ADCY5","risk":0.0009933755},"198":{"gene":"ADCY2","risk":0.0009933755},"199":{"gene":"ADCY8","risk":0.0009931698},"200":{"gene":"ADCY6","risk":0.0009929096},"201":{"gene":"ADCY4","risk":0.0009927561},"202":{"gene":"EPOR","risk":0.000978664},"203":{"gene":"FKBP1A","risk":0.0009664416},"204":{"gene":"PDE8B","risk":0.0009619311},"205":{"gene":"NT5C2","risk":0.0008858317},"206":{"gene":"NT5C1A","risk":0.0008827379},"207":{"gene":"NT5C1B-RDH14","risk":0.0008826112},"209":{"gene":"NT5C","risk":0.0008822934},"210":{"gene":"NT5M","risk":0.0008821234},"211":{"gene":"NDUFAF2","risk":0.0008815302},"212":{"gene":"NT5E","risk":0.0008800159},"213":{"gene":"SDHB","risk":0.0008537394},"214":{"gene":"HPRT1","risk":0.0008092947},"215":{"gene":"GNG2","risk":0.0007797547},"216":{"gene":"AMPD1","risk":0.000778662},"217":{"gene":"AMPD3","risk":0.0007785252},"218":{"gene":"AMPD2","risk":0.0007781828},"219":{"gene":"ADCY1","risk":0.0007663554},"220":{"gene":"PRKACA","risk":0.0007662756},"221":{"gene":"CLCN2","risk":0.0007573172},"222":{"gene":"ARHGEF9","risk":0.0007477973},"223":{"gene":"MT-CO1","risk":0.0007100523},"224":{"gene":"GMPR2","risk":0.000709954},"225":{"gene":"GMPR","risk":0.0007099238},"226":{"gene":"GLRA3","risk":0.0007073137},"227":{"gene":"GLRA2","risk":0.0007072631},"228":{"gene":"GNAS","risk":0.0007044893},"229":{"gene":"GMPS","risk":0.0006987325},"230":{"gene":"MT-CO3","risk":0.0006879144},"231":{"gene":"DCK","risk":0.0006713952},"232":{"gene":"AGT","risk":0.0006665675},"233":{"gene":"ADK","risk":0.0006629201},"234":{"gene":"ADSL","risk":0.0006575387},"235":{"gene":"ENTPD6","risk":0.0006544543},"236":{"gene":"ENTPD5","risk":0.000654401},"237":{"gene":"CANT1","risk":0.0006538727},"238":{"gene":"ENTPD4","risk":0.0006537651},"239":{"gene":"GNAI3","risk":0.0006525885},"240":{"gene":"COX6A1","risk":0.0006442487},"241":{"gene":"MYC","risk":0.0006401626},"242":{"gene":"PRKACB","risk":0.0006340866},"243":{"gene":"CHRNA6","risk":0.0006239019},"244":{"gene":"CHRNA3","risk":0.0006223319},"245":{"gene":"CHRNB4","risk":0.0006221805},"246":{"gene":"CHRNA7","risk":0.0006221185},"247":{"gene":"COX7A2L","risk":0.0006181555},"248":{"gene":"COX7C","risk":0.0006173123},"249":{"gene":"COX5B","risk":0.0006161131},"250":{"gene":"CHRNB3","risk":0.000615392},"252":{"gene":"CHRNA2","risk":0.0006120413},"253":{"gene":"COX6C","risk":0.0006108361},"254":{"gene":"COX5A","risk":0.0006100635},"255":{"gene":"PRKACG","risk":0.0006047103},"256":{"gene":"ETFB","risk":0.0006016413},"257":{"gene":"COX4I1","risk":0.0006015602},"258":{"gene":"CHRNA5","risk":0.0006009103},"259":{"gene":"CHRND","risk":0.0006004619},"260":{"gene":"COX8A","risk":0.0005834809},"261":{"gene":"SDHA","risk":0.0005830649},"263":{"gene":"MT-CO2","risk":0.0005739846},"264":{"gene":"APP","risk":0.0005682242},"265":{"gene":"POMC","risk":0.00056388},"266":{"gene":"GNAT3","risk":0.0005630936},"267":{"gene":"CACNG2","risk":0.0005624346},"268":{"gene":"DYNC1H1","risk":0.0005580898},"269":{"gene":"HSP90AA1","risk":0.0005560945},"270":{"gene":"AK8","risk":0.0005554784},"271":{"gene":"AK4","risk":0.0005552864},"272":{"gene":"AK7","risk":0.000555035},"273":{"gene":"GUK1","risk":0.0005541241},"274":{"gene":"ADCY10","risk":0.0005514773},"275":{"gene":"AK1","risk":0.0005514698},"276":{"gene":"GNAI1","risk":0.0005505359},"277":{"gene":"AK2","risk":0.000549451},"278":{"gene":"AK5","risk":0.0005494371},"279":{"gene":"DYNC1I2","risk":0.0005454228},"280":{"gene":"ATG4A","risk":0.0005436369},"281":{"gene":"CACNG3","risk":0.0005421395},"282":{"gene":"CACNG8","risk":0.0005421268},"283":{"gene":"CACNG7","risk":0.0005302321},"284":{"gene":"MAX","risk":0.000525623},"285":{"gene":"GCG","risk":0.000515362},"286":{"gene":"CHRNB1","risk":0.0005088286},"287":{"gene":"GCGR","risk":0.0005051565},"289":{"gene":"NPS","risk":0.0004942711},"290":{"gene":"NPSR1","risk":0.0004941927},"291":{"gene":"AVP","risk":0.0004928063},"292":{"gene":"SRC","risk":0.0004923256},"293":{"gene":"AKT1","risk":0.000482768},"294":{"gene":"PPP1CA","risk":0.0004819714},"295":{"gene":"PPP1CC","risk":0.0004784269},"296":{"gene":"ETFA","risk":0.0004658292},"297":{"gene":"VIP","risk":0.0004605072},"298":{"gene":"CAMK2A","risk":0.0004589359},"299":{"gene":"PPP2R1A","risk":0.0004581988},"300":{"gene":"PPP1CB","risk":0.0004566409},"301":{"gene":"ADM","risk":0.0004548727},"302":{"gene":"CALCB","risk":0.0004548012},"304":{"gene":"MC5R","risk":0.000453575},"305":{"gene":"MC2R","risk":0.0004533643},"306":{"gene":"DRD5","risk":0.0004533503},"307":{"gene":"MC3R","risk":0.0004532137},"308":{"gene":"VIPR1","risk":0.0004531805},"309":{"gene":"TAAR1","risk":0.000453136},"310":{"gene":"GPBAR1","risk":0.0004531359},"311":{"gene":"ADM2","risk":0.0004531254},"312":{"gene":"PTH2","risk":0.0004531203},"313":{"gene":"GLP2R","risk":0.0004531165},"314":{"gene":"GHRHR","risk":0.0004531161},"315":{"gene":"PTH2R","risk":0.0004531131},"316":{"gene":"VIPR2","risk":0.0004531118},"317":{"gene":"GIPR","risk":0.0004531117},"318":{"gene":"GHRH","risk":0.0004531004},"319":{"gene":"PTH","risk":0.0004530991},"320":{"gene":"MC1R","risk":0.000453087},"321":{"gene":"HTR4","risk":0.0004519495},"322":{"gene":"PTGDR","risk":0.0004516845},"323":{"gene":"CRH","risk":0.0004509828},"324":{"gene":"HTR7","risk":0.0004506753},"325":{"gene":"ADCYAP1","risk":0.0004504565},"326":{"gene":"SCT","risk":0.0004502206},"327":{"gene":"HTR6","risk":0.0004502086},"328":{"gene":"CREBBP","risk":0.0004500436},"329":{"gene":"PTH1R","risk":0.0004495832},"330":{"gene":"PTGER4","risk":0.0004492301},"331":{"gene":"ADCYAP1R1","risk":0.0004488488},"332":{"gene":"MC4R","risk":0.0004488309},"333":{"gene":"CALCA","risk":0.0004488129},"334":{"gene":"CRHR2","risk":0.00044793},"335":{"gene":"YWHAB","risk":0.0004477045},"336":{"gene":"PTGIR","risk":0.0004475826},"337":{"gene":"PTHLH","risk":0.0004448464},"338":{"gene":"FSHR","risk":0.0004429639},"339":{"gene":"TSHR","risk":0.0004428527},"340":{"gene":"CACNG4","risk":0.000442551},"341":{"gene":"LHCGR","risk":0.0004418344},"342":{"gene":"IAPP","risk":0.0004394251},"343":{"gene":"ADRB3","risk":0.0004392693},"344":{"gene":"GUCY2D","risk":0.0004387976},"345":{"gene":"GRIA1","risk":0.0004386584},"346":{"gene":"HRH2","risk":0.0004377106},"347":{"gene":"GUCY2F","risk":0.0004357993},"348":{"gene":"GIP","risk":0.0004356987},"349":{"gene":"UBQLN1","risk":0.0004322008},"350":{"gene":"RAB7A","risk":0.0004305215},"352":{"gene":"SCTR","risk":0.0004261377},"355":{"gene":"LPAR1","risk":0.0004241947},"356":{"gene":"DYNC1I1","risk":0.0004233852},"357":{"gene":"NPR1","risk":0.0004217327},"358":{"gene":"GUCY2C","risk":0.0004213263},"359":{"gene":"PKM","risk":0.0004202269},"360":{"gene":"NME1","risk":0.0004200026},"361":{"gene":"DYNLL1","risk":0.0004195113},"362":{"gene":"DYNC1LI2","risk":0.0004194208},"363":{"gene":"TP53","risk":0.0004189435},"364":{"gene":"NPR2","risk":0.0004187917},"365":{"gene":"LPAR2","risk":0.0004186048},"366":{"gene":"LPAR3","risk":0.00041798},"367":{"gene":"LPAR5","risk":0.0004160661},"368":{"gene":"PRKX","risk":0.0004151996},"369":{"gene":"GRIA2","risk":0.0004150186},"370":{"gene":"SAA1","risk":0.0004147767},"371":{"gene":"UBB","risk":0.0004126382},"372":{"gene":"CAMK2G","risk":0.0004057242},"373":{"gene":"CACNG5","risk":0.0004051244},"374":{"gene":"EP300","risk":0.0004049777},"375":{"gene":"NME2","risk":0.000403017},"376":{"gene":"PIK3CA","risk":0.0004018597},"378":{"gene":"RPS27A","risk":0.0004005347},"380":{"gene":"CDK1","risk":0.0004003589},"381":{"gene":"NME4","risk":0.0003989853},"382":{"gene":"RILP","risk":0.0003983175},"383":{"gene":"CAMK2B","risk":0.0003977434},"384":{"gene":"GRIA4","risk":0.0003976967},"385":{"gene":"PAFAH1B1","risk":0.000396858},"386":{"gene":"ANXA1","risk":0.0003967828},"387":{"gene":"PMCH","risk":0.0003958338},"388":{"gene":"FPR2","risk":0.0003947282},"389":{"gene":"BDKRB1","risk":0.0003946878},"390":{"gene":"CASR","risk":0.0003937948},"391":{"gene":"NMUR2","risk":0.0003935133},"392":{"gene":"NMUR1","risk":0.0003935099},"393":{"gene":"MCHR2","risk":0.0003934946},"395":{"gene":"NMS","risk":0.0003934878},"396":{"gene":"GPR17","risk":0.000393471},"397":{"gene":"NMU","risk":0.0003934702},"398":{"gene":"CAMK2D","risk":0.000393364},"399":{"gene":"MCHR1","risk":0.0003932172},"400":{"gene":"NME1-NME2","risk":0.0003904092},"401":{"gene":"NME3","risk":0.0003871833},"402":{"gene":"PFDN2","risk":0.0003848092},"403":{"gene":"IMPDH1","risk":0.0003828496},"404":{"gene":"DCTN2","risk":0.0003827665},"405":{"gene":"MAPK1","risk":0.0003825882},"406":{"gene":"UBA52","risk":0.0003806959},"407":{"gene":"CACNG1","risk":0.0003789694},"408":{"gene":"DYNC1LI1","risk":0.0003785812},"410":{"gene":"PFDN4","risk":0.000376531},"411":{"gene":"NME5","risk":0.0003763299},"412":{"gene":"CACNA2D1","risk":0.0003758274},"413":{"gene":"DCTN3","risk":0.0003756991},"414":{"gene":"NME6","risk":0.0003756885},"415":{"gene":"NME7","risk":0.0003753191},"416":{"gene":"POLR2K","risk":0.0003743426},"417":{"gene":"CCT8","risk":0.0003737616},"418":{"gene":"CCT3","risk":0.0003722212},"420":{"gene":"PFDN1","risk":0.0003721097},"421":{"gene":"CCT2","risk":0.0003715698},"422":{"gene":"PFDN5","risk":0.000371562},"424":{"gene":"CCT7","risk":0.0003704389},"425":{"gene":"POLR2E","risk":0.0003700786},"426":{"gene":"CCT5","risk":0.0003686704},"427":{"gene":"ACTR1A","risk":0.0003679912},"429":{"gene":"POLR2F","risk":0.0003669796},"430":{"gene":"POLR2L","risk":0.000366325},"431":{"gene":"TCP1","risk":0.0003655612},"432":{"gene":"COX4I2","risk":0.0003649547},"433":{"gene":"CCT6A","risk":0.0003638553},"434":{"gene":"AKAP9","risk":0.0003621311},"435":{"gene":"PPP2CA","risk":0.000362116},"436":{"gene":"YWHAG","risk":0.0003578656},"437":{"gene":"CXCL12","risk":0.0003574365},"438":{"gene":"YWHAE","risk":0.0003567823},"439":{"gene":"CCT4","risk":0.0003547407},"440":{"gene":"CACNB1","risk":0.0003523025},"441":{"gene":"APOA1","risk":0.0003517883},"442":{"gene":"IMPDH2","risk":0.0003463683},"443":{"gene":"CXCR4","risk":0.0003446362},"444":{"gene":"RGS19","risk":0.0003434698},"446":{"gene":"PPBP","risk":0.0003432837},"447":{"gene":"GIMAP6","risk":0.0003431308},"448":{"gene":"CACNB4","risk":0.0003430475},"449":{"gene":"PLK1","risk":0.0003413214},"450":{"gene":"STBD1","risk":0.0003396003},"451":{"gene":"DRD2","risk":0.0003391142},"452":{"gene":"ATIC","risk":0.0003383824},"453":{"gene":"CACNB3","risk":0.0003378435},"454":{"gene":"COX6A2","risk":0.0003377498},"455":{"gene":"CACNB2","risk":0.0003368205},"456":{"gene":"RGS18","risk":0.000336424},"457":{"gene":"TUBG1","risk":0.0003358536},"458":{"gene":"HRAS","risk":0.0003355166},"459":{"gene":"ATP6AP2","risk":0.0003345375},"461":{"gene":"CACNA2D4","risk":0.0003308486},"462":{"gene":"CLASP1","risk":0.0003304801},"463":{"gene":"CACNG6","risk":0.0003298482},"466":{"gene":"TBCE","risk":0.0003269039},"467":{"gene":"CCR5","risk":0.0003266637},"468":{"gene":"SCN1B","risk":0.0003264644},"470":{"gene":"CCR3","risk":0.0003247106},"471":{"gene":"TBCD","risk":0.0003235472},"472":{"gene":"OPRK1","risk":0.0003231876},"473":{"gene":"SCN2B","risk":0.000322222},"475":{"gene":"RASGRF1","risk":0.0003190636},"476":{"gene":"FPR1","risk":0.0003182663},"477":{"gene":"TBCA","risk":0.0003178326},"478":{"gene":"TBCB","risk":0.000317465},"479":{"gene":"CHRM2","risk":0.0003169821},"480":{"gene":"DRD4","risk":0.0003165294},"481":{"gene":"SDHC","risk":0.0003163921},"482":{"gene":"DNM1","risk":0.0003151105},"483":{"gene":"MAPRE1","risk":0.0003149156},"484":{"gene":"SDHD","risk":0.0003147695},"485":{"gene":"MED1","risk":0.0003138383},"486":{"gene":"HTR5A","risk":0.0003136273},"487":{"gene":"PPP2CB","risk":0.0003131107},"488":{"gene":"SCN3B","risk":0.000312138},"489":{"gene":"DRD3","risk":0.0003116098},"490":{"gene":"CHRM4","risk":0.0003115469},"491":{"gene":"CNR1","risk":0.0003115028},"493":{"gene":"HTR1F","risk":0.0003114615},"494":{"gene":"HTR1E","risk":0.0003114609},"495":{"gene":"HTR1A","risk":0.000311327},"496":{"gene":"HTR1B","risk":0.0003113015},"497":{"gene":"PRKAR2B","risk":0.0003109558},"498":{"gene":"MTNR1B","risk":0.0003105687},"499":{"gene":"MTNR1A","risk":0.0003105525},"500":{"gene":"GNAQ","risk":0.0003094226},"501":{"gene":"EGFR","risk":0.0003091096},"502":{"gene":"CXCR3","risk":0.0003088994},"503":{"gene":"CALM1","risk":0.000308268},"504":{"gene":"CXCR2","risk":0.0003079565},"505":{"gene":"JAK2","risk":0.0003075462},"506":{"gene":"CXCR1","risk":0.0003063125},"507":{"gene":"SCN4B","risk":0.0003062073},"508":{"gene":"ENTPD2","risk":0.0003047151},"509":{"gene":"NTPCR","risk":0.0003043269},"510":{"gene":"CCR10","risk":0.0003030567},"511":{"gene":"CXCR5","risk":0.0003029063},"512":{"gene":"CXCR6","risk":0.0003028694},"513":{"gene":"CCR9","risk":0.0003027208},"514":{"gene":"CCR4","risk":0.0003025792},"515":{"gene":"CCR8","risk":0.0003025651},"516":{"gene":"CCR7","risk":0.0003025562},"517":{"gene":"CCR6","risk":0.0003025155},"518":{"gene":"SCN8A","risk":0.0003023648},"520":{"gene":"POLR3A","risk":0.0003019928},"521":{"gene":"PDYN","risk":0.0003019045},"522":{"gene":"CCR1","risk":0.000301883},"523":{"gene":"C3","risk":0.0003012084},"524":{"gene":"ATP6V0E2","risk":0.0003011277},"525":{"gene":"ATP6V0B","risk":0.000301015},"526":{"gene":"S1PR3","risk":0.0003009197},"527":{"gene":"CXCL8","risk":0.0003007056},"528":{"gene":"RAF1","risk":0.0003006674},"529":{"gene":"POLR3F","risk":0.0003003828},"530":{"gene":"S1PR1","risk":0.0003002569},"531":{"gene":"ATP6V0E1","risk":0.000300155},"533":{"gene":"ATP6V1G3","risk":0.0003000427}}